{
  "id": 17109378,
  "name": "lab5",
  "full_name": "yanshu/lab5",
  "owner": {
    "login": "yanshu",
    "id": 3340553,
    "avatar_url": "https://avatars2.githubusercontent.com/u/3340553?v=3",
    "gravatar_id": "",
    "url": "https://api.github.com/users/yanshu",
    "html_url": "https://github.com/yanshu",
    "followers_url": "https://api.github.com/users/yanshu/followers",
    "following_url": "https://api.github.com/users/yanshu/following{/other_user}",
    "gists_url": "https://api.github.com/users/yanshu/gists{/gist_id}",
    "starred_url": "https://api.github.com/users/yanshu/starred{/owner}{/repo}",
    "subscriptions_url": "https://api.github.com/users/yanshu/subscriptions",
    "organizations_url": "https://api.github.com/users/yanshu/orgs",
    "repos_url": "https://api.github.com/users/yanshu/repos",
    "events_url": "https://api.github.com/users/yanshu/events{/privacy}",
    "received_events_url": "https://api.github.com/users/yanshu/received_events",
    "type": "User",
    "site_admin": false
  },
  "private": false,
  "html_url": "https://github.com/yanshu/lab5",
  "description": null,
  "fork": false,
  "url": "https://api.github.com/repos/yanshu/lab5",
  "forks_url": "https://api.github.com/repos/yanshu/lab5/forks",
  "keys_url": "https://api.github.com/repos/yanshu/lab5/keys{/key_id}",
  "collaborators_url": "https://api.github.com/repos/yanshu/lab5/collaborators{/collaborator}",
  "teams_url": "https://api.github.com/repos/yanshu/lab5/teams",
  "hooks_url": "https://api.github.com/repos/yanshu/lab5/hooks",
  "issue_events_url": "https://api.github.com/repos/yanshu/lab5/issues/events{/number}",
  "events_url": "https://api.github.com/repos/yanshu/lab5/events",
  "assignees_url": "https://api.github.com/repos/yanshu/lab5/assignees{/user}",
  "branches_url": "https://api.github.com/repos/yanshu/lab5/branches{/branch}",
  "tags_url": "https://api.github.com/repos/yanshu/lab5/tags",
  "blobs_url": "https://api.github.com/repos/yanshu/lab5/git/blobs{/sha}",
  "git_tags_url": "https://api.github.com/repos/yanshu/lab5/git/tags{/sha}",
  "git_refs_url": "https://api.github.com/repos/yanshu/lab5/git/refs{/sha}",
  "trees_url": "https://api.github.com/repos/yanshu/lab5/git/trees{/sha}",
  "statuses_url": "https://api.github.com/repos/yanshu/lab5/statuses/{sha}",
  "languages_url": "https://api.github.com/repos/yanshu/lab5/languages",
  "stargazers_url": "https://api.github.com/repos/yanshu/lab5/stargazers",
  "contributors_url": "https://api.github.com/repos/yanshu/lab5/contributors",
  "subscribers_url": "https://api.github.com/repos/yanshu/lab5/subscribers",
  "subscription_url": "https://api.github.com/repos/yanshu/lab5/subscription",
  "commits_url": "https://api.github.com/repos/yanshu/lab5/commits{/sha}",
  "git_commits_url": "https://api.github.com/repos/yanshu/lab5/git/commits{/sha}",
  "comments_url": "https://api.github.com/repos/yanshu/lab5/comments{/number}",
  "issue_comment_url": "https://api.github.com/repos/yanshu/lab5/issues/comments{/number}",
  "contents_url": "https://api.github.com/repos/yanshu/lab5/contents/{+path}",
  "compare_url": "https://api.github.com/repos/yanshu/lab5/compare/{base}...{head}",
  "merges_url": "https://api.github.com/repos/yanshu/lab5/merges",
  "archive_url": "https://api.github.com/repos/yanshu/lab5/{archive_format}{/ref}",
  "downloads_url": "https://api.github.com/repos/yanshu/lab5/downloads",
  "issues_url": "https://api.github.com/repos/yanshu/lab5/issues{/number}",
  "pulls_url": "https://api.github.com/repos/yanshu/lab5/pulls{/number}",
  "milestones_url": "https://api.github.com/repos/yanshu/lab5/milestones{/number}",
  "notifications_url": "https://api.github.com/repos/yanshu/lab5/notifications{?since,all,participating}",
  "labels_url": "https://api.github.com/repos/yanshu/lab5/labels{/name}",
  "releases_url": "https://api.github.com/repos/yanshu/lab5/releases{/id}",
  "deployments_url": "https://api.github.com/repos/yanshu/lab5/deployments",
  "created_at": "2014-02-23T14:25:51Z",
  "updated_at": "2014-02-28T15:11:57Z",
  "pushed_at": "2014-02-28T15:11:57Z",
  "git_url": "git://github.com/yanshu/lab5.git",
  "ssh_url": "git@github.com:yanshu/lab5.git",
  "clone_url": "https://github.com/yanshu/lab5.git",
  "svn_url": "https://github.com/yanshu/lab5",
  "homepage": null,
  "size": 272,
  "stargazers_count": 0,
  "watchers_count": 0,
  "language": "Julia",
  "has_issues": true,
  "has_projects": true,
  "has_downloads": true,
  "has_wiki": true,
  "has_pages": false,
  "forks_count": 0,
  "mirror_url": null,
  "open_issues_count": 0,
  "forks": 0,
  "open_issues": 0,
  "watchers": 0,
  "default_branch": "master",
  "permissions": {
    "admin": false,
    "push": false,
    "pull": true
  },
  "network_count": 0,
  "subscribers_count": 1
}
