{
  "id": 48703361,
  "name": "TinyTimeModels.jl",
  "full_name": "GordStephen/TinyTimeModels.jl",
  "owner": {
    "login": "GordStephen",
    "id": 2753264,
    "avatar_url": "https://avatars0.githubusercontent.com/u/2753264?v=3",
    "gravatar_id": "",
    "url": "https://api.github.com/users/GordStephen",
    "html_url": "https://github.com/GordStephen",
    "followers_url": "https://api.github.com/users/GordStephen/followers",
    "following_url": "https://api.github.com/users/GordStephen/following{/other_user}",
    "gists_url": "https://api.github.com/users/GordStephen/gists{/gist_id}",
    "starred_url": "https://api.github.com/users/GordStephen/starred{/owner}{/repo}",
    "subscriptions_url": "https://api.github.com/users/GordStephen/subscriptions",
    "organizations_url": "https://api.github.com/users/GordStephen/orgs",
    "repos_url": "https://api.github.com/users/GordStephen/repos",
    "events_url": "https://api.github.com/users/GordStephen/events{/privacy}",
    "received_events_url": "https://api.github.com/users/GordStephen/received_events",
    "type": "User",
    "site_admin": false
  },
  "private": false,
  "html_url": "https://github.com/GordStephen/TinyTimeModels.jl",
  "description": "Parameter estimation for univariate local-level structural time series models, with diffuse state initialization and optional linear regression terms",
  "fork": false,
  "url": "https://api.github.com/repos/GordStephen/TinyTimeModels.jl",
  "forks_url": "https://api.github.com/repos/GordStephen/TinyTimeModels.jl/forks",
  "keys_url": "https://api.github.com/repos/GordStephen/TinyTimeModels.jl/keys{/key_id}",
  "collaborators_url": "https://api.github.com/repos/GordStephen/TinyTimeModels.jl/collaborators{/collaborator}",
  "teams_url": "https://api.github.com/repos/GordStephen/TinyTimeModels.jl/teams",
  "hooks_url": "https://api.github.com/repos/GordStephen/TinyTimeModels.jl/hooks",
  "issue_events_url": "https://api.github.com/repos/GordStephen/TinyTimeModels.jl/issues/events{/number}",
  "events_url": "https://api.github.com/repos/GordStephen/TinyTimeModels.jl/events",
  "assignees_url": "https://api.github.com/repos/GordStephen/TinyTimeModels.jl/assignees{/user}",
  "branches_url": "https://api.github.com/repos/GordStephen/TinyTimeModels.jl/branches{/branch}",
  "tags_url": "https://api.github.com/repos/GordStephen/TinyTimeModels.jl/tags",
  "blobs_url": "https://api.github.com/repos/GordStephen/TinyTimeModels.jl/git/blobs{/sha}",
  "git_tags_url": "https://api.github.com/repos/GordStephen/TinyTimeModels.jl/git/tags{/sha}",
  "git_refs_url": "https://api.github.com/repos/GordStephen/TinyTimeModels.jl/git/refs{/sha}",
  "trees_url": "https://api.github.com/repos/GordStephen/TinyTimeModels.jl/git/trees{/sha}",
  "statuses_url": "https://api.github.com/repos/GordStephen/TinyTimeModels.jl/statuses/{sha}",
  "languages_url": "https://api.github.com/repos/GordStephen/TinyTimeModels.jl/languages",
  "stargazers_url": "https://api.github.com/repos/GordStephen/TinyTimeModels.jl/stargazers",
  "contributors_url": "https://api.github.com/repos/GordStephen/TinyTimeModels.jl/contributors",
  "subscribers_url": "https://api.github.com/repos/GordStephen/TinyTimeModels.jl/subscribers",
  "subscription_url": "https://api.github.com/repos/GordStephen/TinyTimeModels.jl/subscription",
  "commits_url": "https://api.github.com/repos/GordStephen/TinyTimeModels.jl/commits{/sha}",
  "git_commits_url": "https://api.github.com/repos/GordStephen/TinyTimeModels.jl/git/commits{/sha}",
  "comments_url": "https://api.github.com/repos/GordStephen/TinyTimeModels.jl/comments{/number}",
  "issue_comment_url": "https://api.github.com/repos/GordStephen/TinyTimeModels.jl/issues/comments{/number}",
  "contents_url": "https://api.github.com/repos/GordStephen/TinyTimeModels.jl/contents/{+path}",
  "compare_url": "https://api.github.com/repos/GordStephen/TinyTimeModels.jl/compare/{base}...{head}",
  "merges_url": "https://api.github.com/repos/GordStephen/TinyTimeModels.jl/merges",
  "archive_url": "https://api.github.com/repos/GordStephen/TinyTimeModels.jl/{archive_format}{/ref}",
  "downloads_url": "https://api.github.com/repos/GordStephen/TinyTimeModels.jl/downloads",
  "issues_url": "https://api.github.com/repos/GordStephen/TinyTimeModels.jl/issues{/number}",
  "pulls_url": "https://api.github.com/repos/GordStephen/TinyTimeModels.jl/pulls{/number}",
  "milestones_url": "https://api.github.com/repos/GordStephen/TinyTimeModels.jl/milestones{/number}",
  "notifications_url": "https://api.github.com/repos/GordStephen/TinyTimeModels.jl/notifications{?since,all,participating}",
  "labels_url": "https://api.github.com/repos/GordStephen/TinyTimeModels.jl/labels{/name}",
  "releases_url": "https://api.github.com/repos/GordStephen/TinyTimeModels.jl/releases{/id}",
  "deployments_url": "https://api.github.com/repos/GordStephen/TinyTimeModels.jl/deployments",
  "created_at": "2015-12-28T17:09:15Z",
  "updated_at": "2016-03-09T21:27:02Z",
  "pushed_at": "2016-03-09T21:25:48Z",
  "git_url": "git://github.com/GordStephen/TinyTimeModels.jl.git",
  "ssh_url": "git@github.com:GordStephen/TinyTimeModels.jl.git",
  "clone_url": "https://github.com/GordStephen/TinyTimeModels.jl.git",
  "svn_url": "https://github.com/GordStephen/TinyTimeModels.jl",
  "homepage": "",
  "size": 11,
  "stargazers_count": 0,
  "watchers_count": 0,
  "language": "Julia",
  "has_issues": true,
  "has_projects": true,
  "has_downloads": true,
  "has_wiki": true,
  "has_pages": false,
  "forks_count": 0,
  "mirror_url": null,
  "open_issues_count": 0,
  "forks": 0,
  "open_issues": 0,
  "watchers": 0,
  "default_branch": "master",
  "permissions": {
    "admin": false,
    "push": false,
    "pull": true
  },
  "network_count": 0,
  "subscribers_count": 1
}
