{
  "id": 65226253,
  "name": "Garbo.jl",
  "full_name": "kpamnany/Garbo.jl",
  "owner": {
    "login": "kpamnany",
    "id": 3784427,
    "avatar_url": "https://avatars2.githubusercontent.com/u/3784427?v=3",
    "gravatar_id": "",
    "url": "https://api.github.com/users/kpamnany",
    "html_url": "https://github.com/kpamnany",
    "followers_url": "https://api.github.com/users/kpamnany/followers",
    "following_url": "https://api.github.com/users/kpamnany/following{/other_user}",
    "gists_url": "https://api.github.com/users/kpamnany/gists{/gist_id}",
    "starred_url": "https://api.github.com/users/kpamnany/starred{/owner}{/repo}",
    "subscriptions_url": "https://api.github.com/users/kpamnany/subscriptions",
    "organizations_url": "https://api.github.com/users/kpamnany/orgs",
    "repos_url": "https://api.github.com/users/kpamnany/repos",
    "events_url": "https://api.github.com/users/kpamnany/events{/privacy}",
    "received_events_url": "https://api.github.com/users/kpamnany/received_events",
    "type": "User",
    "site_admin": false
  },
  "private": false,
  "html_url": "https://github.com/kpamnany/Garbo.jl",
  "description": null,
  "fork": false,
  "url": "https://api.github.com/repos/kpamnany/Garbo.jl",
  "forks_url": "https://api.github.com/repos/kpamnany/Garbo.jl/forks",
  "keys_url": "https://api.github.com/repos/kpamnany/Garbo.jl/keys{/key_id}",
  "collaborators_url": "https://api.github.com/repos/kpamnany/Garbo.jl/collaborators{/collaborator}",
  "teams_url": "https://api.github.com/repos/kpamnany/Garbo.jl/teams",
  "hooks_url": "https://api.github.com/repos/kpamnany/Garbo.jl/hooks",
  "issue_events_url": "https://api.github.com/repos/kpamnany/Garbo.jl/issues/events{/number}",
  "events_url": "https://api.github.com/repos/kpamnany/Garbo.jl/events",
  "assignees_url": "https://api.github.com/repos/kpamnany/Garbo.jl/assignees{/user}",
  "branches_url": "https://api.github.com/repos/kpamnany/Garbo.jl/branches{/branch}",
  "tags_url": "https://api.github.com/repos/kpamnany/Garbo.jl/tags",
  "blobs_url": "https://api.github.com/repos/kpamnany/Garbo.jl/git/blobs{/sha}",
  "git_tags_url": "https://api.github.com/repos/kpamnany/Garbo.jl/git/tags{/sha}",
  "git_refs_url": "https://api.github.com/repos/kpamnany/Garbo.jl/git/refs{/sha}",
  "trees_url": "https://api.github.com/repos/kpamnany/Garbo.jl/git/trees{/sha}",
  "statuses_url": "https://api.github.com/repos/kpamnany/Garbo.jl/statuses/{sha}",
  "languages_url": "https://api.github.com/repos/kpamnany/Garbo.jl/languages",
  "stargazers_url": "https://api.github.com/repos/kpamnany/Garbo.jl/stargazers",
  "contributors_url": "https://api.github.com/repos/kpamnany/Garbo.jl/contributors",
  "subscribers_url": "https://api.github.com/repos/kpamnany/Garbo.jl/subscribers",
  "subscription_url": "https://api.github.com/repos/kpamnany/Garbo.jl/subscription",
  "commits_url": "https://api.github.com/repos/kpamnany/Garbo.jl/commits{/sha}",
  "git_commits_url": "https://api.github.com/repos/kpamnany/Garbo.jl/git/commits{/sha}",
  "comments_url": "https://api.github.com/repos/kpamnany/Garbo.jl/comments{/number}",
  "issue_comment_url": "https://api.github.com/repos/kpamnany/Garbo.jl/issues/comments{/number}",
  "contents_url": "https://api.github.com/repos/kpamnany/Garbo.jl/contents/{+path}",
  "compare_url": "https://api.github.com/repos/kpamnany/Garbo.jl/compare/{base}...{head}",
  "merges_url": "https://api.github.com/repos/kpamnany/Garbo.jl/merges",
  "archive_url": "https://api.github.com/repos/kpamnany/Garbo.jl/{archive_format}{/ref}",
  "downloads_url": "https://api.github.com/repos/kpamnany/Garbo.jl/downloads",
  "issues_url": "https://api.github.com/repos/kpamnany/Garbo.jl/issues{/number}",
  "pulls_url": "https://api.github.com/repos/kpamnany/Garbo.jl/pulls{/number}",
  "milestones_url": "https://api.github.com/repos/kpamnany/Garbo.jl/milestones{/number}",
  "notifications_url": "https://api.github.com/repos/kpamnany/Garbo.jl/notifications{?since,all,participating}",
  "labels_url": "https://api.github.com/repos/kpamnany/Garbo.jl/labels{/name}",
  "releases_url": "https://api.github.com/repos/kpamnany/Garbo.jl/releases{/id}",
  "deployments_url": "https://api.github.com/repos/kpamnany/Garbo.jl/deployments",
  "created_at": "2016-08-08T17:51:12Z",
  "updated_at": "2016-08-08T18:37:17Z",
  "pushed_at": "2016-10-21T09:02:11Z",
  "git_url": "git://github.com/kpamnany/Garbo.jl.git",
  "ssh_url": "git@github.com:kpamnany/Garbo.jl.git",
  "clone_url": "https://github.com/kpamnany/Garbo.jl.git",
  "svn_url": "https://github.com/kpamnany/Garbo.jl",
  "homepage": null,
  "size": 14,
  "stargazers_count": 0,
  "watchers_count": 0,
  "language": "Julia",
  "has_issues": true,
  "has_projects": true,
  "has_downloads": true,
  "has_wiki": true,
  "has_pages": false,
  "forks_count": 0,
  "mirror_url": null,
  "open_issues_count": 1,
  "forks": 0,
  "open_issues": 1,
  "watchers": 0,
  "default_branch": "master",
  "permissions": {
    "admin": false,
    "push": false,
    "pull": true
  },
  "network_count": 0,
  "subscribers_count": 0
}
